{"_id":"92a98d87d4bb1dc2611a","tittle":"Nineteen Eighty-Four","author":"George Orwell","cover_image_url":"https://covers.openlibrary.org/b/id/9267242-L.jpg","description":"Donec sollicitudin molestie malesuada. Vestibulum ac diam sit amet quam vehicula elementum sed sit amet dui. Vivamus magna justo, lacinia eget consectetur sed, convallis at tellus. Cras ultricies ligula sed magna dictum porta.","categories":["korean","mystery","programming","suspense","mystery"],"isbn":"2266002669","status":"available","copies_available":2,"copies_lended":0,"createdAt":"2021-10-30T06:54:26.625Z","updatedAt":"2021-10-30T06:54:26.625Z"}